py_backwards_packager/__init__.py
py_backwards_packager/bootstrap.py
py_backwards_packager/const.py
py_backwards_packager/core.py
py_backwards_packager-0.1.1.dist-info/DESCRIPTION.rst
py_backwards_packager-0.1.1.dist-info/METADATA
py_backwards_packager-0.1.1.dist-info/RECORD
py_backwards_packager-0.1.1.dist-info/WHEEL
py_backwards_packager-0.1.1.dist-info/entry_points.txt
py_backwards_packager-0.1.1.dist-info/metadata.json
py_backwards_packager-0.1.1.dist-info/top_level.txt
