Metadata-Version: 2.0
Name: py-backwards-packager
Version: 0.1.1
Summary: Setuptools integration with py-backwards
Home-page: https://github.com/nvbn/py-backwards-packager
Author: Vladimir Iakovlev
Author-email: nvbn.rm@gmail.com
License: MIT
Platform: UNKNOWN
Requires-Dist: py-backwards
